rossum_deploy/__init__.py
rossum_deploy/constants.py
rossum_deploy/models.py
rossum_deploy/py.typed
rossum_deploy/workspace.py
rossum_deploy-0.1.0.post0.dist-info/METADATA
rossum_deploy-0.1.0.post0.dist-info/WHEEL
rossum_deploy-0.1.0.post0.dist-info/top_level.txt
rossum_deploy-0.1.0.post0.dist-info/RECORD
