Metadata-Version: 2.4
Name: rossum-deploy
Version: 0.1.0.post0
Summary: Minimalistic pull/diff/push deployment for Rossum configurations
Author-email: "Dan Stancl (Rossum AI)" <daniel.stancl@gmail.com>
License: MIT
Keywords: rossum,deployment,configuration-management
Requires-Python: >=3.12
Requires-Dist: pydantic>=2.0.0
Requires-Dist: rossum-api>=3.7.0
Provides-Extra: tests
Requires-Dist: pytest>=7.0.0; extra == "tests"
Requires-Dist: pytest-asyncio>=0.21.0; extra == "tests"
Requires-Dist: pytest-cov>=4.0.0; extra == "tests"
